Connnet/__init__.py
Connnet/network.cpython-312-darwin.so
Connnet-0.2.2.dist-info/LICENSE.txt
Connnet-0.2.2.dist-info/METADATA
Connnet-0.2.2.dist-info/WHEEL
Connnet-0.2.2.dist-info/top_level.txt
Connnet-0.2.2.dist-info/RECORD
