Metadata-Version: 2.1
Name: Connnet
Version: 0.2.2
Summary: A network generation package
Author: YN
Author-email: 
Classifier: Programming Language :: Python :: 3
Classifier: License :: OSI Approved :: MIT License
Classifier: Operating System :: OS Independent
Requires-Python: >=3.6
License-File: LICENSE.txt
